Metadata-Version: 2.1
Name: lawr
Version: 0.1
Summary: Удобный класс для работы с файлами.
Author-email: BusinessJson6@gmail.com
